setup.py
bin/tesla_generate_and_replace_injections
bin/tesla_generate_reduced_bank
bin/tesla_workflow
gstlal_tesla/__init__.py
gstlal_tesla/tesla_generate_and_replace_injections.py
gstlal_tesla/tesla_generate_reduced_bank.py
gstlal_tesla/tesla_workflow.py
gstlal_tesla.egg-info/PKG-INFO
gstlal_tesla.egg-info/SOURCES.txt
gstlal_tesla.egg-info/dependency_links.txt
gstlal_tesla.egg-info/top_level.txt
gstlal_tesla/config/__init__.py
gstlal_tesla/config/gstlal.py
gstlal_tesla/config/inspiral.py
gstlal_tesla/dags/__init__.py
gstlal_tesla/dags/generate_injections.py
gstlal_tesla/dags/layers/__init__.py
gstlal_tesla/dags/layers/generate_injections.py